apply_patch_py/__init__.py
apply_patch_py/applier.py
apply_patch_py/cli.py
apply_patch_py/constants.py
apply_patch_py/models.py
apply_patch_py/parser.py
apply_patch_py/search.py
apply_patch_py/utils.py
apply_patch_py-0.4.0.dist-info/METADATA
apply_patch_py-0.4.0.dist-info/WHEEL
apply_patch_py-0.4.0.dist-info/entry_points.txt
apply_patch_py-0.4.0.dist-info/licenses/LICENSE
apply_patch_py-0.4.0.dist-info/RECORD
