Metadata-Version: 2.4
Name: apply-patch-py
Version: 0.4.0
Summary: Apply Codex-style patch blocks (*** Begin Patch ... *** End Patch) to a file
Project-URL: Homepage, https://github.com/marcius-llmus/apply-patch-py
Project-URL: Repository, https://github.com/marcius-llmus/apply-patch-py
Project-URL: Issues, https://github.com/marcius-llmus/apply-patch-py/issues
Project-URL: Changelog, https://github.com/marcius-llmus/apply-patch-py/releases
Author: marcin
License: MIT License
License-File: LICENSE
Keywords: apply,codex,diff,llm,patch,tooling
Classifier: Development Status :: 3 - Alpha
Classifier: Intended Audience :: Developers
Classifier: License :: OSI Approved :: MIT License
Classifier: Programming Language :: Python :: 3
Classifier: Programming Language :: Python :: 3 :: Only
Classifier: Programming Language :: Python :: 3.13
Classifier: Topic :: Software Development :: Build Tools
Classifier: Topic :: Software Development :: Version Control
Classifier: Typing :: Typed
Requires-Python: >=3.13
Requires-Dist: aiofiles>=24.1.0
